pyhud/__init__.py
hudd-0.0.0a0.dist-info/METADATA
hudd-0.0.0a0.dist-info/WHEEL
hudd-0.0.0a0.dist-info/top_level.txt
hudd-0.0.0a0.dist-info/RECORD
